LICENSE.md
MANIFEST.in
README.md
setup.py
geoLibDPP.egg-info/PKG-INFO
geoLibDPP.egg-info/SOURCES.txt
geoLibDPP.egg-info/dependency_links.txt
geoLibDPP.egg-info/top_level.txt
geo_lib/__init__.py
geo_lib/city.py
geo_lib/geo_lib_requesthandler.py