Metadata-Version: 2.1
Name: geoLibDPP
Version: 1.4
Summary: A module for DPP classes
Home-page: UNKNOWN
Author: Pavel Babrovich
Author-email: 251223@student.pwr.edu.pl
License: UNKNOWN
Platform: UNKNOWN
